{
    "@id": "dr:data/physical-parameter/diftrbbo",
    "@type": "dr:variable",
    "cf-standard-name": {
        "@id": "cf:standard-name/0 checked out of 1"
    },
    "cf-standard-name-exists": false,
    "cmor-variables": [
        {
            "@id": "dr:variables/oclim.diftrbbo"
        },
        {
            "@id": "dr:variables/oclim.diftrbbo2d"
        }
    ],
    "comments": "",
    "created": "2024-07-12T09:06:25.000Z",
    "data-protection-consent": "",
    "description": "Parameterized mesoscale eddy advection occurs on a spatial scale of many tens of kilometres and an evolutionary time of weeks(sometimes called bolus advection). Reference: James C. McWilliams 2016, Submesoscale currents in the ocean, Proceedings of the Royal Society A: Mathematical, Physical and Engineering Sciences, volume 472, issue 2189. DOI: 10.1098/rspa.2016.0117. \n",
    "edited-by-author-teams": "",
    "justification-for-inclusion": "",
    "last-modified-by": "Data Request co-leads",
    "name": "diftrbbo",
    "name-validation": 1,
    "processing-comment": "",
    "processing-note": "",
    "proposer-email": "",
    "proposer-name": "",
    "provenance": "CMIP5_Oclim",
    "status": "Existing physical parameter",
    "tagged-author-team": "",
    "title": "Ocean Tracer Bolus Biharmonic Diffusivity",
    "uid": "b21073e1a8fa421ecd21766bc8442acd",
    "units": "m4 s-1",
    "review": {
        "atmosphere-review-comments": "",
        "atmosphere-review-comments-copy": "",
        "atmosphere-team-review-status": "",
        "atmosphere-team-review-status-copy-2": "",
        "atmosphere-team-review-status-copy-4": "",
        "atmosphere-team-review-status-copy-5": "",
        "atmosphere-team-review-status-copy-6": ""
    }
}