{
    "@id": "dr:data/physical-parameter/gpp",
    "@type": "dr:variable",
    "cf-standard-name": {
        "@id": "cf:standard-name/0 checked out of 1"
    },
    "cf-standard-name-exists": false,
    "cmor-variables": [
        {
            "@id": "dr:variables/e3hr.gpp"
        },
        {
            "@id": "dr:variables/lmon.gpp"
        }
    ],
    "comments": "",
    "created": "2024-07-12T09:06:25.000Z",
    "data-protection-consent": "",
    "description": "The rate of synthesis of biomass from inorganic precursors by autotrophs (\"producers\") expressed as the mass of carbon which it contains. For example, photosynthesis in plants or phytoplankton. The producers also respire some of this biomass and the difference is referred to as the net primary production. \n",
    "edited-by-author-teams": "",
    "justification-for-inclusion": "",
    "last-modified-by": "Data Request co-leads",
    "name": "gpp",
    "name-validation": 1,
    "processing-comment": "",
    "processing-note": "",
    "proposer-email": "",
    "proposer-name": "",
    "provenance": "CMIP5_Lmon,PMIP3_Lclim,PMIP3_Lmon,SPECS_Lmon",
    "status": "Existing physical parameter",
    "tagged-author-team": "",
    "title": "Carbon Mass Flux out of Atmosphere Due to Gross Primary Production on Land [kgC m-2 s-1]",
    "uid": "89c4bb4f45a0182fc00a1b86b13241a5",
    "units": "kg m-2 s-1",
    "review": {
        "atmosphere-review-comments": "",
        "atmosphere-review-comments-copy": "",
        "atmosphere-team-review-status": "",
        "atmosphere-team-review-status-copy-2": "",
        "atmosphere-team-review-status-copy-4": "",
        "atmosphere-team-review-status-copy-5": "",
        "atmosphere-team-review-status-copy-6": ""
    }
}