{
    "@id": "dr:data/physical-parameter/prveg",
    "@type": "dr:variable",
    "cf-standard-name": {
        "@id": "cf:standard-name/0 checked out of 1"
    },
    "cf-standard-name-exists": false,
    "cmor-variables": [
        {
            "@id": "dr:variables/eday.prveg"
        },
        {
            "@id": "dr:variables/lmon.prveg"
        }
    ],
    "comments": "",
    "created": "2024-07-12T09:06:25.000Z",
    "data-protection-consent": "",
    "description": "The precipitation flux that is intercepted by the vegetation canopy (if present in model) before reaching the ground.\n",
    "edited-by-author-teams": "",
    "justification-for-inclusion": "",
    "last-modified-by": "Data Request co-leads",
    "name": "prveg",
    "name-validation": 1,
    "processing-comment": "",
    "processing-note": "",
    "proposer-email": "",
    "proposer-name": "",
    "provenance": "CMIP5_Lmon,PMIP3_Lclim,PMIP3_Lmon,SPECS_Lmon",
    "status": "Existing physical parameter",
    "tagged-author-team": "",
    "title": "Precipitation onto Canopy",
    "uid": "e54a3eda3d5fc42a9cd1354038ad45ed",
    "units": "kg m-2 s-1",
    "review": {
        "atmosphere-review-comments": "",
        "atmosphere-review-comments-copy": "",
        "atmosphere-team-review-status": "",
        "atmosphere-team-review-status-copy-2": "",
        "atmosphere-team-review-status-copy-4": "",
        "atmosphere-team-review-status-copy-5": "",
        "atmosphere-team-review-status-copy-6": ""
    }
}