{
    "@id": "dr:data/physical-parameter/sfy",
    "@type": "dr:variable",
    "cf-standard-name": {
        "@id": "cf:standard-name/0 checked out of 1"
    },
    "cf-standard-name-exists": false,
    "cmor-variables": [
        {
            "@id": "dr:variables/omon.sfy"
        }
    ],
    "comments": "",
    "created": "2024-10-07T07:13:53.000Z",
    "data-protection-consent": true,
    "description": "",
    "edited-by-author-teams": "",
    "justification-for-inclusion": "For regional budgets of salt in eddy-permitting ocean models, this term is necessary because the salt transport has an eddy component (arising from salinity-velocity correlations in time) that cannot be recomputed from monthly salinity and velocity.\n",
    "last-modified-by": "Data Request co-leads",
    "name": "sfy",
    "name-validation": 1,
    "processing-comment": "",
    "processing-note": "",
    "proposer-email": "anne-marie.treguier@univ-brest.fr",
    "proposer-name": "Anne Marie Treguier",
    "provenance": "",
    "status": "New",
    "tagged-author-team": [
        "Ocean & sea-ice"
    ],
    "title": "Ocean Salt y Transport",
    "uid": "f86eb6c9-8ca1-11ef-944e-41a8eb05f654",
    "units": "kg s-1",
    "review": {
        "atmosphere-review-comments": "",
        "atmosphere-review-comments-copy": "",
        "atmosphere-team-review-status": "",
        "atmosphere-team-review-status-copy-2": "",
        "atmosphere-team-review-status-copy-4": "",
        "atmosphere-team-review-status-copy-5": "",
        "atmosphere-team-review-status-copy-6": ""
    }
}