{
    "@id": "dr:data/physical-parameter/sialgc",
    "@type": "dr:variable",
    "cf-standard-name": {
        "@id": "cf:standard-name/"
    },
    "cf-standard-name-exists": false,
    "cmor-variables": [
        {
            "@id": "dr:variables/simon.sialgc"
        },
        {
            "@id": "dr:variables/siday.sialgc"
        }
    ],
    "comments": "\"Reconsidering the name of the physical parameter \"\"sic\"\"\"",
    "created": "2024-09-12T21:26:58.000Z",
    "data-protection-consent": true,
    "description": "",
    "edited-by-author-teams": "",
    "justification-for-inclusion": "Some CMIP7 models now have sea ice biogeochemistry included and are interested in saving these variables. Models that include sea-ice biogeochemistry support closing the carbon and nutrient s' cycles in the sea-ice zone.\n\n",
    "last-modified-by": "Data Request co-leads",
    "name": "sialgc",
    "name-validation": 1,
    "processing-comment": "",
    "processing-note": "",
    "proposer-email": "letizia.tedesco@environment.fi",
    "proposer-name": "Letizia Tedesco",
    "provenance": "",
    "status": "Under review",
    "tagged-author-team": [
        "Ocean & sea-ice"
    ],
    "title": "Total Ice Algal Carbon Amount ",
    "uid": "f86eb6cb-8ca1-11ef-944e-41a8eb05f654",
    "units": "mol m-2",
    "review": {
        "atmosphere-review-comments": "",
        "atmosphere-review-comments-copy": "",
        "atmosphere-team-review-status": "",
        "atmosphere-team-review-status-copy-2": "In progress",
        "atmosphere-team-review-status-copy-4": "",
        "atmosphere-team-review-status-copy-5": "",
        "atmosphere-team-review-status-copy-6": ""
    }
}