{
    "@id": "dr:data/variables/3hr.swh",
    "@type": "dr:variable",
    "cf-standard-name": {
        "@id": "cf:standard-name/"
    },
    "cf-standard-name-exists": false,
    "cmip7-variable-groups": "",
    "compound-name": "3hr.swh",
    "description": "Wind driven surface gravity waves at the ocean surface, generated by the wave model , wave Height\n",
    "frequency": [
        {
            "@id": "mip-cmor-tables:auxillary/frequency/3hr"
        }
    ],
    "modeling-realm": [
        {
            "@id": "mip-cmor-tables:auxillary/realm/ocean"
        }
    ],
    "positive-direction": "",
    "processing-note": "Grid point normal output from wave model\n",
    "provenance": "",
    "status": "New",
    "table": [
        "3hr"
    ],
    "theme": [
        "Ocean & sea-ice"
    ],
    "title": "Total Wave Significant Wave Height",
    "type": "real",
    "uid": "83bbfc72-7f07-11ef-9308-b1dd71e64bec",
    "variable-is-included-in-esm-bcv-v1.3": "",
    "review": {
        "atmosphere-author-team-review": "",
        "atmosphere-review-comment": "",
        "cross-thematic-group-review-comment": "",
        "cross-thematic-team-review": "",
        "earth-system-author-team-review": "",
        "impacts-&-adaptation-author-team-review": "",
        "land-&-land-ice-author-team-review": "",
        "ocean-&-sea-ice-author-team-review": ""
    },
    "priority": {
        "priority-1-(cmip6)": "",
        "priority-1-(cmip6)----old": "",
        "priority-2-(cmip6---old": "",
        "priority-2-(cmip6)": "",
        "priority-3-(cmip6---old)": "",
        "priority-3-(cmip6)": ""
    },
    "rank": {
        "min-rank": null,
        "rank-by-file-count": null,
        "rank-by-submissions": null,
        "rank-by-volume": null
    }
}