{
    "@id": "dr:data/variables/aermon.lwp",
    "@type": "dr:variable",
    "brand-(dr)-[link]": "twm-z0-hxy-amn",
    "brand-(wip)-[link]": "tavg-z0-hxy-x",
    "cf-standard-name": {
        "@id": "cf:standard-name/atmosphere_mass_content_of_cloud_liquid_water"
    },
    "cf-standard-name-exists": true,
    "cmip7-variable-groups": "aerchemmip_2d_monthly, FireMIP_monthly",
    "compound-name": "AERmon.lwp",
    "description": "The total mass of liquid water in cloud per unit area.\n",
    "frequency": [
        {
            "@id": "mip-cmor-tables:auxillary/frequency/mon"
        }
    ],
    "modeling-realm": [
        {
            "@id": "mip-cmor-tables:auxillary/realm/aerosol"
        }
    ],
    "opportunity-status-(from-cmip7-variable-groups)": [
        "Under review",
        "Accepted"
    ],
    "positive-direction": "",
    "processing-note": "",
    "provenance": "AERmon ((isd.003))",
    "status": "CMIP6 CMOR variable",
    "table": [
        "AERmon"
    ],
    "theme": "",
    "title": "Liquid Water Path",
    "type": "real",
    "uid": "19bf71ae-81b1-11e6-92de-ac72891c3257",
    "variable-is-included-in-esm-bcv-v1.3": "",
    "review": {
        "atmosphere-author-team-review": "",
        "atmosphere-review-comment": "",
        "cross-thematic-group-review-comment": "",
        "cross-thematic-team-review": "",
        "earth-system-author-team-review": "",
        "impacts-&-adaptation-author-team-review": "",
        "land-&-land-ice-author-team-review": "",
        "ocean-&-sea-ice-author-team-review": ""
    },
    "priority": {
        "priority-1-(cmip6)": "",
        "priority-1-(cmip6)----old": [
            "AerChemMIP",
            "PMIP"
        ],
        "priority-2-(cmip6---old": "",
        "priority-2-(cmip6)": "",
        "priority-3-(cmip6---old)": "",
        "priority-3-(cmip6)": ""
    },
    "rank": {
        "min-rank": 228,
        "rank-by-file-count": 343,
        "rank-by-submissions": 228,
        "rank-by-volume": 828
    }
}