{
    "@id": "dr:data/variables/edayz.epfz",
    "@type": "dr:variable",
    "brand-(dr)-[link]": "twm-p39-hy-zmeana",
    "brand-(wip)-[link]": "tavg-p39-hy-x",
    "cf-standard-name": {
        "@id": "cf:standard-name/upward_eliassen_palm_flux_in_air"
    },
    "cf-standard-name-exists": true,
    "cmip7-variable-groups": "dynvar_basic",
    "compound-name": "EdayZ.epfz",
    "description": "zonal mean; hence YZT\n",
    "opportunity-status-(from-cmip7-variable-groups)": [
        "Accepted"
    ],
    "positive-direction": "up",
    "processing-note": "",
    "provenance": "DynVarMIP [DYVR_daily_a]",
    "status": "CMIP6 CMOR variable",
    "theme": "",
    "title": "Upward Component of the Eliassen-Palm Flux",
    "type": "real",
    "uid": "8b97e000-4a5b-11e6-9cd2-ac72891c3257",
    "variable-is-included-in-esm-bcv-v1.3": "",
    "review": {
        "atmosphere-author-team-review": "",
        "atmosphere-review-comment": "",
        "cross-thematic-group-review-comment": "",
        "cross-thematic-team-review": "",
        "earth-system-author-team-review": "",
        "impacts-&-adaptation-author-team-review": "",
        "land-&-land-ice-author-team-review": "",
        "ocean-&-sea-ice-author-team-review": ""
    },
    "priority": {
        "priority-1-(cmip6)": "",
        "priority-1-(cmip6)----old": [
            "DynVarMIP"
        ],
        "priority-2-(cmip6---old": "",
        "priority-2-(cmip6)": "",
        "priority-3-(cmip6---old)": "",
        "priority-3-(cmip6)": ""
    },
    "rank": {
        "min-rank": 548,
        "rank-by-file-count": 1088,
        "rank-by-submissions": 548,
        "rank-by-volume": 1007
    }
}