{
    "@id": "dr:data/variables/edayz.ta",
    "@type": "dr:variable",
    "brand-(dr)-[link]": "twm-p39-hy-amna",
    "brand-(wip)-[link]": "tavg-p39-hy-x",
    "cf-standard-name": {
        "@id": "cf:standard-name/air_temperature"
    },
    "cf-standard-name-exists": true,
    "cmip7-variable-groups": "dynvar_basic",
    "compound-name": "EdayZ.ta",
    "description": "Zonal mean temperature of air with the extended number of vertical levels.\n\n",
    "modeling-realm": [
        {
            "@id": "mip-cmor-tables:auxillary/realm/atmos"
        }
    ],
    "opportunity-status-(from-cmip7-variable-groups)": [
        "Accepted"
    ],
    "positive-direction": "",
    "processing-note": "",
    "provenance": "DAMIP [DAMIP_day_zm]",
    "status": "CMIP6 CMOR variable",
    "theme": [
        "Atmosphere"
    ],
    "title": "Zonal mean air temperature",
    "type": "real",
    "uid": "8b8fa6e2-4a5b-11e6-9cd2-ac72891c3257",
    "variable-is-included-in-esm-bcv-v1.3": "",
    "review": {
        "atmosphere-author-team-review": "",
        "atmosphere-review-comment": "",
        "cross-thematic-group-review-comment": "",
        "cross-thematic-team-review": "",
        "earth-system-author-team-review": "",
        "impacts-&-adaptation-author-team-review": "",
        "land-&-land-ice-author-team-review": "",
        "ocean-&-sea-ice-author-team-review": ""
    },
    "priority": {
        "priority-1-(cmip6)": "",
        "priority-1-(cmip6)----old": [
            "DAMIP"
        ],
        "priority-2-(cmip6---old": "",
        "priority-2-(cmip6)": "",
        "priority-3-(cmip6---old)": "",
        "priority-3-(cmip6)": ""
    },
    "rank": {
        "min-rank": 400,
        "rank-by-file-count": 400,
        "rank-by-submissions": 402,
        "rank-by-volume": 693
    }
}