{
    "@id": "dr:data/variables/emon.raother",
    "@type": "dr:variable",
    "brand-(dr)-[link]": "tmn-z0-hxy-amnla",
    "brand-(wip)-[link]": "tavg-z0-hxy-lnd",
    "cf-standard-name": {
        "@id": "cf:standard-name/surface_upward_mass_flux_of_carbon_dioxide_expressed_as_carbon_due_to_plant_respiration_in_miscellaneous_living_matter"
    },
    "cf-standard-name-exists": true,
    "cmip7-variable-groups": "c4mip_land_carbon_cycle_tier2",
    "compound-name": "Emon.raOther",
    "description": "added for completeness with Ra\\_root\n",
    "modeling-realm": [
        {
            "@id": "mip-cmor-tables:auxillary/realm/land"
        }
    ],
    "opportunity-status-(from-cmip7-variable-groups)": [
        "Under review"
    ],
    "positive-direction": "",
    "processing-note": "",
    "provenance": "C4MIP [C_LandT2]",
    "status": "CMIP6 CMOR variable",
    "theme": "",
    "title": "Total Respiration from Other Pools (not Leaves Stem or Roots) as Carbon Mass Flux [kgC m-2 s-1]",
    "type": "real",
    "uid": "e70755cc-aa7f-11e6-9a4a-5404a60d96b5",
    "variable-is-included-in-esm-bcv-v1.3": "",
    "review": {
        "atmosphere-author-team-review": "",
        "atmosphere-review-comment": "",
        "cross-thematic-group-review-comment": "",
        "cross-thematic-team-review": "",
        "earth-system-author-team-review": "",
        "impacts-&-adaptation-author-team-review": "",
        "land-&-land-ice-author-team-review": "",
        "ocean-&-sea-ice-author-team-review": ""
    },
    "priority": {
        "priority-1-(cmip6)": "",
        "priority-1-(cmip6)----old": "",
        "priority-2-(cmip6---old": [
            "C4MIP"
        ],
        "priority-2-(cmip6)": "",
        "priority-3-(cmip6---old)": "",
        "priority-3-(cmip6)": ""
    },
    "rank": {
        "min-rank": 9999,
        "rank-by-file-count": null,
        "rank-by-submissions": null,
        "rank-by-volume": null
    }
}