{
    "@id": "dr:data/variables/oday.zos_dup",
    "@type": "dr:variable",
    "brand-(dr)-[link]": "tmn-z0-hxy-amns",
    "brand-(wip)-[link]": "tavg-z0-hxy-sea",
    "cf-standard-name": {
        "@id": "cf:standard-name/sea_surface_height_above_geoid"
    },
    "cf-standard-name-exists": true,
    "cmip7-variable-groups": "",
    "compound-name": "Oday.zos_dup",
    "description": "This is the dynamic sea level, so should have zero global area mean. It should not include inverse barometer depressions from sea ice.\n",
    "opportunity-status-(from-cmip7-variable-groups)": "",
    "positive-direction": "",
    "processing-note": "",
    "provenance": "",
    "status": "Under review",
    "theme": [
        "Ocean & sea-ice"
    ],
    "title": "Sea Surface Height above Geoid",
    "type": "real",
    "uid": "83bbfb68-7f07-11ef-9308-b1dd71e64bec",
    "variable-is-included-in-esm-bcv-v1.3": "",
    "review": {
        "atmosphere-author-team-review": "",
        "atmosphere-review-comment": "",
        "cross-thematic-group-review-comment": "",
        "cross-thematic-team-review": "",
        "earth-system-author-team-review": "",
        "impacts-&-adaptation-author-team-review": "",
        "land-&-land-ice-author-team-review": "",
        "ocean-&-sea-ice-author-team-review": "In progress"
    },
    "priority": {
        "priority-1-(cmip6)": "",
        "priority-1-(cmip6)----old": "",
        "priority-2-(cmip6---old": "",
        "priority-2-(cmip6)": "",
        "priority-3-(cmip6---old)": "",
        "priority-3-(cmip6)": ""
    },
    "rank": {
        "min-rank": null,
        "rank-by-file-count": null,
        "rank-by-submissions": null,
        "rank-by-volume": null
    }
}