{
    "@id": "dr:data/variables/omon.vmo",
    "@type": "dr:variable",
    "brand-(dr)-[link]": "tmn-ol-hxy-amns",
    "brand-(wip)-[link]": "tavg-l-hxy-sea",
    "cf-standard-name": {
        "@id": "cf:standard-name/ocean_mass_y_transport"
    },
    "cf-standard-name-exists": true,
    "cmip7-variable-groups": "baseline_monthly, aerchemmip_3d_monthly, SO_BGC-cloud_ocean_monthly, tipmip_baseline, omip_transports_high_priority",
    "compound-name": "Omon.vmo",
    "description": "Y-ward mass transport from residual mean (resolved plus parameterized) advective transport.\n",
    "modeling-realm": [
        {
            "@id": "mip-cmor-tables:auxillary/realm/ocean"
        }
    ],
    "opportunity-status-(from-cmip7-variable-groups)": [
        "Accepted",
        "Under review"
    ],
    "positive-direction": "",
    "processing-note": "Report on native horizontal grid. Online mapping to depth/pressure vertical grid if depth or pressure are not native.\n",
    "provenance": "Omon ((isd.003))",
    "status": "CMIP6 CMOR variable",
    "theme": "",
    "title": "Ocean Mass Y Transport",
    "type": "real",
    "uid": "baa598c0-e5dd-11e5-8482-ac72891c3257",
    "variable-is-included-in-esm-bcv-v1.3": "1 checked out of 1",
    "review": {
        "atmosphere-author-team-review": "",
        "atmosphere-review-comment": "",
        "cross-thematic-group-review-comment": "",
        "cross-thematic-team-review": "",
        "earth-system-author-team-review": "",
        "impacts-&-adaptation-author-team-review": "",
        "land-&-land-ice-author-team-review": "",
        "ocean-&-sea-ice-author-team-review": ""
    },
    "priority": {
        "priority-1-(cmip6)": "",
        "priority-1-(cmip6)----old": [
            "CMIP",
            "CMIP5",
            "VIACSAB"
        ],
        "priority-2-(cmip6---old": [
            "CFMIP",
            "VIACSAB"
        ],
        "priority-2-(cmip6)": "",
        "priority-3-(cmip6---old)": "",
        "priority-3-(cmip6)": ""
    },
    "rank": {
        "min-rank": 47,
        "rank-by-file-count": 124,
        "rank-by-submissions": 125,
        "rank-by-volume": 47
    }
}