{
    "@id": "dr:data/variables/omon.wfonocorr",
    "@type": "dr:variable",
    "brand-(dr)-[link]": "tmn-z0-hxy-amns",
    "brand-(wip)-[link]": "tavg-z0-hxy-sea",
    "cf-standard-name": {
        "@id": "cf:standard-name/water_flux_into_sea_water_without_flux_correction"
    },
    "cf-standard-name-exists": true,
    "cmip7-variable-groups": "",
    "compound-name": "Omon.wfonocorr",
    "description": "Computed as the water flux (without flux correction) into the ocean divided by the area of the ocean portion of the grid cell.\n",
    "frequency": [
        {
            "@id": "mip-cmor-tables:auxillary/frequency/mon"
        }
    ],
    "modeling-realm": [
        {
            "@id": "mip-cmor-tables:auxillary/realm/ocean"
        }
    ],
    "positive-direction": "",
    "processing-note": "This should be the sum of the various processes contributing to water fluxes. Report on native horizontal grid as well as mapped onto sphere.\n",
    "provenance": "Omon ((isd.003))",
    "status": "CMIP6 CMOR variable",
    "table": [
        "Omon"
    ],
    "theme": "",
    "title": "Water Flux into Sea Water Without Flux Correction",
    "type": "real",
    "uid": "baa639b0-e5dd-11e5-8482-ac72891c3257",
    "variable-is-included-in-esm-bcv-v1.3": "",
    "review": {
        "atmosphere-author-team-review": "",
        "atmosphere-review-comment": "",
        "cross-thematic-group-review-comment": "",
        "cross-thematic-team-review": "",
        "earth-system-author-team-review": "",
        "impacts-&-adaptation-author-team-review": "",
        "land-&-land-ice-author-team-review": "",
        "ocean-&-sea-ice-author-team-review": ""
    },
    "priority": {
        "priority-1-(cmip6)": "",
        "priority-1-(cmip6)----old": [
            "CMIP",
            "CMIP5",
            "DAMIP",
            "VIACSAB"
        ],
        "priority-2-(cmip6---old": "",
        "priority-2-(cmip6)": "",
        "priority-3-(cmip6---old)": "",
        "priority-3-(cmip6)": ""
    },
    "rank": {
        "min-rank": 186,
        "rank-by-file-count": 186,
        "rank-by-submissions": 533,
        "rank-by-volume": 805
    }
}