{
    "@id": "dr:data/variables/omon.volcello",
    "@type": "dr:variable",
    "cf-standard-name": {
        "@id": "cf:standard-name/ocean_volume"
    },
    "cf-standard-name-exists": true,
    "cmip7-variable-groups": "ocean_coordinates, ref_ocean_and_seaice, omip_geometry_low_priority, ocean_grid",
    "compound-name": "Omon.volcello",
    "description": "For oceans with more than 1 mesh (e.g. staggered grids), report areas that apply to surface vertical fluxes of energy. If this field is time-dependent then save it instead as one of your Omon and Odec fields\n",
    "frequency": [
        {
            "@id": "mip-cmor-tables:auxillary/frequency/mon"
        }
    ],
    "modeling-realm": [
        {
            "@id": "mip-cmor-tables:auxillary/realm/ocean"
        }
    ],
    "positive-direction": "",
    "processing-note": "a 3-d field: For oceans with more than 1 mesh, report on grid that applies to temperature\n",
    "provenance": "Omon ((isd.003))",
    "status": "CMIP6 CMOR variable",
    "table": [
        "Omon"
    ],
    "theme": "",
    "title": "Ocean Grid-Cell Volume",
    "type": "real",
    "uid": "e0739eaa-e1ab-11e7-9db4-1c4d70487308",
    "variable-is-included-in-esm-bcv-v1.3": "0 checked out of 1",
    "review": {
        "atmosphere-author-team-review": "",
        "atmosphere-review-comment": "",
        "cross-thematic-group-review-comment": "",
        "cross-thematic-team-review": "",
        "earth-system-author-team-review": "",
        "impacts-&-adaptation-author-team-review": "",
        "land-&-land-ice-author-team-review": "",
        "ocean-&-sea-ice-author-team-review": ""
    },
    "priority": {
        "priority-1-(cmip6)": "",
        "priority-1-(cmip6)----old": [
            "CMIP5"
        ],
        "priority-2-(cmip6---old": "",
        "priority-2-(cmip6)": "",
        "priority-3-(cmip6---old)": "",
        "priority-3-(cmip6)": ""
    },
    "rank": {
        "min-rank": 164,
        "rank-by-file-count": 471,
        "rank-by-submissions": 692,
        "rank-by-volume": 164
    }
}