{
    "@id": "dr:data/variables/oyr.bddtdisi",
    "@type": "dr:variable",
    "cf-standard-name": {
        "@id": "cf:standard-name/tendency_of_mole_concentration_of_dissolved_inorganic_silicon_in_sea_water_due_to_biological_processes"
    },
    "cf-standard-name-exists": true,
    "cmip7-variable-groups": "",
    "compound-name": "Oyr.bddtdisi",
    "description": "Net of biological terms in time rate of change of dissolved inorganic silicon\n",
    "frequency": [
        {
            "@id": "mip-cmor-tables:auxillary/frequency/yr"
        }
    ],
    "modeling-realm": [
        {
            "@id": "mip-cmor-tables:auxillary/realm/ocnbgchem"
        }
    ],
    "positive-direction": "",
    "processing-note": "",
    "provenance": "Oyr ((isd.003))",
    "status": "CMIP6 CMOR variable",
    "table": [
        "Oyr"
    ],
    "theme": "",
    "title": "Rate of Change of Dissolved Inorganic Silicon Due to Biological Activity",
    "type": "real",
    "uid": "ba9efa42-e5dd-11e5-8482-ac72891c3257",
    "variable-is-included-in-esm-bcv-v1.3": "",
    "review": {
        "atmosphere-author-team-review": "",
        "atmosphere-review-comment": "",
        "cross-thematic-group-review-comment": "",
        "cross-thematic-team-review": "",
        "earth-system-author-team-review": "",
        "impacts-&-adaptation-author-team-review": "",
        "land-&-land-ice-author-team-review": "",
        "ocean-&-sea-ice-author-team-review": ""
    },
    "priority": {
        "priority-1-(cmip6)": "",
        "priority-1-(cmip6)----old": [
            "VIACSAB"
        ],
        "priority-2-(cmip6---old": [
            "VIACSAB"
        ],
        "priority-2-(cmip6)": "",
        "priority-3-(cmip6---old)": [
            "CMIP5"
        ],
        "priority-3-(cmip6)": ""
    },
    "rank": {
        "min-rank": 658,
        "rank-by-file-count": 1050,
        "rank-by-submissions": 1230,
        "rank-by-volume": 658
    }
}