{
    "@id": "dr:data/variables/simon.simpconc",
    "@type": "dr:variable",
    "cf-standard-name": {
        "@id": "cf:standard-name/area_fraction"
    },
    "cf-standard-name-exists": true,
    "cmip7-variable-groups": "seaice_state_monthly_advanced, paleo_cryosphere, paleo_cryosphere_high_priority",
    "compound-name": "SImon.simpconc",
    "description": "Percentage of sea ice, by area, which is covered by melt ponds, giving equal weight to every square metre of sea ice .\n",
    "frequency": [
        {
            "@id": "mip-cmor-tables:auxillary/frequency/mon"
        }
    ],
    "modeling-realm": [
        {
            "@id": "mip-cmor-tables:auxillary/realm/seaice"
        }
    ],
    "positive-direction": "",
    "processing-note": "",
    "provenance": "SIMIP [seaicemon]",
    "status": "CMIP6 CMOR variable",
    "table": [
        "SImon"
    ],
    "theme": "",
    "title": "Percentage Cover of Sea Ice by Meltpond",
    "type": "real",
    "uid": "71238a60-faa7-11e6-bfb7-ac72891c3257",
    "variable-is-included-in-esm-bcv-v1.3": "",
    "review": {
        "atmosphere-author-team-review": "",
        "atmosphere-review-comment": "",
        "cross-thematic-group-review-comment": "",
        "cross-thematic-team-review": "",
        "earth-system-author-team-review": "",
        "impacts-&-adaptation-author-team-review": "",
        "land-&-land-ice-author-team-review": "",
        "ocean-&-sea-ice-author-team-review": ""
    },
    "priority": {
        "priority-1-(cmip6)": "",
        "priority-1-(cmip6)----old": [
            "CMIP"
        ],
        "priority-2-(cmip6---old": "",
        "priority-2-(cmip6)": "",
        "priority-3-(cmip6---old)": [
            "SIMIP"
        ],
        "priority-3-(cmip6)": ""
    },
    "rank": {
        "min-rank": 839,
        "rank-by-file-count": 1203,
        "rank-by-submissions": 839,
        "rank-by-volume": 1408
    }
}